punt/__init__.py
punt-1.15.1.dist-info/licenses/LICENSE
punt-1.15.1.dist-info/METADATA
punt-1.15.1.dist-info/WHEEL
punt-1.15.1.dist-info/entry_points.txt
punt-1.15.1.dist-info/top_level.txt
punt-1.15.1.dist-info/RECORD
