Metadata-Version: 2.4
Name: punt
Version: 1.15.1
Summary: Monitor file changes, and run script on changes.
Author-email: "Colin T.A. Gray" <colinta@gmail.com>
License: BSD
Project-URL: Homepage, https://github.com/colinta/punt
Project-URL: Bug Tracker, https://github.com/colinta/punt/issues
Keywords: terminal,command,shell
Classifier: Programming Language :: Python
Classifier: Development Status :: 5 - Production/Stable
Classifier: Environment :: Console
Classifier: License :: OSI Approved :: BSD License
Classifier: Operating System :: OS Independent
Classifier: Intended Audience :: End Users/Desktop
Classifier: Intended Audience :: Developers
Classifier: Intended Audience :: System Administrators
Classifier: Topic :: Software Development
Requires-Python: >=3.7
License-File: LICENSE
Requires-Dist: docopt==0.6.2
Requires-Dist: watchdog==2.0.2
Dynamic: license-file
